spectresc.cpython-312-darwin.so
spectresc-1.0.4.dist-info/RECORD
spectresc-1.0.4.dist-info/LICENSE
spectresc-1.0.4.dist-info/WHEEL
spectresc-1.0.4.dist-info/top_level.txt
spectresc-1.0.4.dist-info/METADATA
