Metadata-Version: 2.1
Name: spectresc
Version: 1.0.4
Summary: SpectRes in C
Download-URL: https://github.com/cylammarco/SpectResC
Author: Marco C Lam
Maintainer: Marco C Lam
Maintainer-email: mlam@roe.ac.uk
Platform: Windows
Platform: Linux
Platform: Mac OS-X
Classifier: License :: OSI Approved :: GNU General Public License v3 (GPLv3)
Classifier: Programming Language :: C
Classifier: Programming Language :: Python :: 3
Classifier: Programming Language :: Python :: 3.8
Classifier: Programming Language :: Python :: 3.9
Classifier: Programming Language :: Python :: 3.10
Classifier: Programming Language :: Python :: 3.11
Classifier: Programming Language :: Python :: 3.12
Classifier: Operating System :: Microsoft :: Windows
Classifier: Operating System :: Unix
Classifier: Operating System :: MacOS
License-File: LICENSE
Requires-Dist: numpy
